pyi_autobundle/__init__.py
pyi_autobundle/cli.py
pyi_autobundle/builder/dryrun.py
pyi_autobundle/builder/pyinstaller_runner.py
pyi_autobundle/builder/runtime_hook_writer.py
pyi_autobundle/builder/spec_generator.py
pyi_autobundle/hooks/hardcoded_hooks.py
pyi_autobundle/hooks/hook_generator.py
pyi_autobundle/scanner/import_scanner.py
pyi_autobundle/scanner/pkg_scanner.py
pyi_autobundle/scanner/tracer.py
pyi_autobundle/utils/buildignore.py
pyi_autobundle/utils/path_resolver.py
pyi_autobundle/utils/resource_resolver.py
pyi_autobundle-0.1.851.dist-info/licenses/LICENSE
pyi_autobundle-0.1.851.dist-info/METADATA
pyi_autobundle-0.1.851.dist-info/WHEEL
pyi_autobundle-0.1.851.dist-info/entry_points.txt
pyi_autobundle-0.1.851.dist-info/top_level.txt
pyi_autobundle-0.1.851.dist-info/RECORD
