Metadata-Version: 2.4
Name: pyi-autobundle
Version: 0.1.851
Summary: Automatic hook and data file bundler for PyInstaller.
Author-email: Aizhee <aizharjamilano@gmail.com>
License: MIT
Keywords: pyinstaller,build,automation
Classifier: Programming Language :: Python :: 3.9
Classifier: Programming Language :: Python :: 3.10
Classifier: Programming Language :: Python :: 3.11
Classifier: License :: OSI Approved :: MIT License
Classifier: Operating System :: OS Independent
Requires-Python: >=3.9
License-File: LICENSE
Requires-Dist: pyinstaller
Dynamic: license-file
